CHANGES.txt
MANIFEST.in
README.txt
setup.py
collective/__init__.py
collective.customizablePersonalizeForm.egg-info/PKG-INFO
collective.customizablePersonalizeForm.egg-info/SOURCES.txt
collective.customizablePersonalizeForm.egg-info/dependency_links.txt
collective.customizablePersonalizeForm.egg-info/entry_points.txt
collective.customizablePersonalizeForm.egg-info/namespace_packages.txt
collective.customizablePersonalizeForm.egg-info/not-zip-safe
collective.customizablePersonalizeForm.egg-info/requires.txt
collective.customizablePersonalizeForm.egg-info/top_level.txt
collective/customizablePersonalizeForm/__init__.py
collective/customizablePersonalizeForm/configure.zcml
collective/customizablePersonalizeForm/overrides.zcml
collective/customizablePersonalizeForm/profiles.zcml
collective/customizablePersonalizeForm/adapters/__init__.py
collective/customizablePersonalizeForm/adapters/adapters.py
collective/customizablePersonalizeForm/adapters/components.py
collective/customizablePersonalizeForm/adapters/configure.zcml
collective/customizablePersonalizeForm/adapters/interfaces.py
collective/customizablePersonalizeForm/browser/__init__.py
collective/customizablePersonalizeForm/browser/account.py
collective/customizablePersonalizeForm/browser/configure.zcml
collective/customizablePersonalizeForm/browser/interfaces.py
collective/customizablePersonalizeForm/browser/personalpreferences.py
collective/customizablePersonalizeForm/browser/templates/extended-account-panel-bare.pt
collective/customizablePersonalizeForm/profiles/default/componentregistry.xml
collective/customizablePersonalizeForm/profiles/default/memberdata_properties.xml
collective/customizablePersonalizeForm/profiles/default/metadata.xml
collective/customizablePersonalizeForm/profiles/default/skins.xml
collective/customizablePersonalizeForm/tests/__init__.py
collective/customizablePersonalizeForm/tests/base.py
collective/customizablePersonalizeForm/tests/test_overrides.py
collective/customizablePersonalizeForm/tests/test_subscriptions.py
docs/HISTORY.txt
docs/INSTALL.txt