Metadata-Version: 1.0
Name: collective.customizablePersonalizeForm
Version: 2.0
Summary: Customizable personalize form for Plone
Home-page: http://svn.plone.org/svn/collective/
Author: Quadra Informatique
Author-email: plone@quadra-informatique.fr
License: GPL
Keywords: personalize_form,customization
Platform: UNKNOWN
Classifier: Programming Language :: Python
Classifier: Development Status :: 5 - Production/Stable
Classifier: Environment :: Web Environment
Classifier: Framework :: Plone
Classifier: Framework :: Zope2
Classifier: Intended Audience :: End Users/Desktop
Classifier: Intended Audience :: Information Technology
Classifier: Intended Audience :: Other Audience
Classifier: Natural Language :: English
Classifier: Natural Language :: French
Classifier: Operating System :: OS Independent
Classifier: Programming Language :: Python :: 2.4
Classifier: Topic :: Utilities
